{
  "ingredientes": {
    "paes": [
      {
        "id": 1,
        "tipo": "Italiano Branco"
      },
      {
        "id": 2,
        "tipo": "3 Queijos"
      },
      {
        "id": 3,
        "tipo": "Parmesão e Orégano"
      },
      {
        "id": 4,
        "tipo": "Integral"
      }
    ],
    "carnes": [
      {
        "id": 1,
        "tipo": "Maminha"
      },
      {
        "id": 2,
        "tipo": "Alcatra"
      },
      {
        "id": 3,
        "tipo": "Picanha"
      },
      {
        "id": 4,
        "tipo": "Veggie burger"
      }
    ],
    "opcionais": [
      {
        "id": 1,
        "tipo": "Bacon"
      },
      {
        "id": 2,
        "tipo": "Cheddar"
      },
      {
        "id": 3,
        "tipo": "Salame"
      },
      {
        "id": 4,
        "tipo": "Tomate"
      },
      {
        "id": 5,
        "tipo": "Cebola roxa"
      },
      {
        "id": 6,
        "tipo": "Pepino"
      }
    ]
  },
  "status": [
    {
      "id": 1,
      "tipo": "Solicitado"
    },
    {
      "id": 2,
      "tipo": "Em produção"
    },
    {
      "id": 3,
      "tipo": "Finalizado"
    }
  ],
  "burgers": [
    {
      "id": "13d2",
      "name": "jorge",
      "carne": "Alcatra",
      "pao": "Italiano Branco",
      "opcionais": [
        "Bacon",
        "Salame",
        "Pepino"
      ],
      "status": "Solicitado"
    },
    {
      "id": "f21e",
      "name": "jolse",
      "carne": "Maminha",
      "pao": "3 Queijos",
      "opcionais": [
        "Cheddar"
      ],
      "status": "Solicitado"
    },
    {
      "id": "c3bc",
      "name": "",
      "carne": "",
      "pao": "",
      "opcionais": [],
      "status": "Solicitado"
    },
    {
      "id": "7ab6",
      "name": "kghjghgj",
      "carne": "Maminha",
      "pao": "Italiano Branco",
      "opcionais": [
        "Bacon"
      ],
      "status": "Solicitado"
    },
    {
      "id": "d4d9",
      "name": "asdha",
      "carne": "Veggie burger",
      "pao": "Integral",
      "opcionais": [
        "Cebola roxa"
      ],
      "status": "Solicitado"
    }
  ]
}